firebaseSimple/firebaseSimple.py
firebaseSimple-0.0.1.dist-info/LICENSE.txt
firebaseSimple-0.0.1.dist-info/METADATA
firebaseSimple-0.0.1.dist-info/WHEEL
firebaseSimple-0.0.1.dist-info/top_level.txt
firebaseSimple-0.0.1.dist-info/RECORD
