Metadata-Version: 2.1
Name: firebaseSimple
Version: 0.0.1
Summary: Experience firebase with hustle free declaration
Home-page: https://github.com/Shikhar0708/firebase_simple
Author: Shikhar Sinha
Author-email: shikharsinha34920@gmail.com
License: UNKNOWN
Project-URL: Bug Tracker, https://github.com/Shikhar0708/firebase_simple/issues
Platform: UNKNOWN
Classifier: Programming Language :: Python :: 3
Classifier: License :: OSI Approved :: MIT License
Classifier: Operating System :: OS Independent
Requires-Python: >=3.6
